gcloud/py.typed
gcloud/rest/kms/__init__.py
gcloud/rest/kms/kms.py
gcloud/rest/kms/py.typed
gcloud/rest/kms/utils.py
gcloud/rest/py.typed
gcloud_rest_kms-5.0.0.dist-info/LICENSE
gcloud_rest_kms-5.0.0.dist-info/METADATA
gcloud_rest_kms-5.0.0.dist-info/WHEEL
gcloud_rest_kms-5.0.0.dist-info/RECORD
