Metadata-Version: 2.1
Name: gcloud-rest-kms
Version: 5.0.0
Summary: Python Client for Google Cloud KMS
Home-page: https://github.com/talkiq/gcloud-aio
License: MIT
Author: Vi Engineering
Author-email: voiceai-eng@dialpad.com
Requires-Python: >=3.8,<4.0
Classifier: Development Status :: 5 - Production/Stable
Classifier: Intended Audience :: Developers
Classifier: License :: OSI Approved :: MIT License
Classifier: Operating System :: OS Independent
Classifier: Programming Language :: Python :: 3
Classifier: Programming Language :: Python :: 3.8
Classifier: Programming Language :: Python :: 3.9
Classifier: Programming Language :: Python :: 3.10
Classifier: Programming Language :: Python :: 3.11
Classifier: Topic :: Internet
Requires-Dist: gcloud-rest-auth (>=3.1.0,<6.0.0)
Project-URL: Repository, https://github.com/talkiq/gcloud-aio
